README.rst
setup.py
auxly/__init__.py
auxly/filesys.py
auxly/listy.py
auxly/shell.py
auxly/stringy.py
auxly/top.py
auxly.egg-info/PKG-INFO
auxly.egg-info/SOURCES.txt
auxly.egg-info/dependency_links.txt
auxly.egg-info/top_level.txt