Metadata-Version: 1.1
Name: auxly
Version: 0.9.0
Summary: Python library for common shell-like script tasks.
Home-page: https://github.com/jeffrimko/Auxly
Author: Jeff Rimko
Author-email: jeffrimko@gmail.com
License: MIT
Keywords: cli script utility library
Platform: UNKNOWN
Classifier: Development Status :: 4 - Beta
Classifier: Topic :: Utilities
Classifier: Programming Language :: Python :: 2.7
Classifier: Programming Language :: Python :: 3
